[1,["b4SOD0HWZJ5o1eWe0jeyvZ@72dea","b4SOD0HWZJ5o1eWe0jeyvZ@bb7f2","f6SJZOjTJB/JrJeh5xTdF7","b4SOD0HWZJ5o1eWe0jeyvZ@a1582","b4SOD0HWZJ5o1eWe0jeyvZ@30732","b4SOD0HWZJ5o1eWe0jeyvZ@9f585","b4SOD0HWZJ5o1eWe0jeyvZ@f1394","b4SOD0HWZJ5o1eWe0jeyvZ@234f9","b4SOD0HWZJ5o1eWe0jeyvZ@75ee4","b4SOD0HWZJ5o1eWe0jeyvZ@50149","b4SOD0HWZJ5o1eWe0jeyvZ@a72ab","b4SOD0HWZJ5o1eWe0jeyvZ@1ad0d","b4SOD0HWZJ5o1eWe0jeyvZ@2224c"],["_parent","node","_mesh","_skeleton","mainTexture","_effectAsset","root","data"],[["cc.Node",["_name","_prefab","_parent","_children","_components","_lpos","_lrot","_lscale","_euler"],2,4,1,2,9,5,5,5,5],["cc.Mesh",["_native","_hash","_struct"],1,11],["cc.Skeleton",["_name","_hash","_joints","_bindposes"],0,12],["cc.Material",["_name","_states","_defines","_props"],0,12],["cc.Prefab",[],3],["cc.Node",["_name","_parent","_children","_prefab","_lpos","_lrot","_lscale","_euler"],2,1,9,4,5,5,5,5],["cc.SkeletalAnimation",["node","__prefab"],3,1,4],["cc.CompPrefabInfo",["fileId"],2],["cc.PrefabInfo",["fileId","instance","targetOverrides","nestedPrefabInstanceRoots","root","asset"],-1,1,1],["cc.SkinnedMeshRenderer",["node","__prefab","_materials","bakeSettings","_skinningRoot","_mesh","_skeleton"],3,1,4,3,4,1,6,6],["cc.ModelBakeSettings",[],3]],[[8,0,1,2,3,4,5,5],[0,0,2,1,5,6,7,8,2],[5,0,1,2,3,4,5,6,7,2],[7,0,2],[1,0,1,2,3],[2,0,1,2,3,4],[0,0,2,3,1,2],[0,0,2,4,1,2],[9,0,1,2,3,4,5,6,1],[10,1],[0,0,2,3,1,5,6,7,8,2],[3,0,1,2,3,4],[4,1],[0,0,3,4,1,2],[6,0,1,1]],[[[[4,".bin",198266407,[{"primitives":[{"primitiveMode":7,"jointMapIndex":0,"vertexBundelIndices":[0],"indexView":{"offset":450432,"length":13656,"count":6828,"stride":2}}],"vertexBundles":[{"view":{"offset":0,"length":450432,"count":6256,"stride":72},"attributes":[{"name":"a_position","format":32,"isNormalized":false},{"name":"a_normal","format":32,"isNormalized":false},{"name":"a_texCoord","format":21,"isNormalized":false},{"name":"a_tangent","format":44,"isNormalized":false},{"name":"a_joints","format":42,"isNormalized":false},{"name":"a_weights","format":44,"isNormalized":false}]}],"jointMaps":[[0,1]]},"minPosition",8,[1,-1.999996304512024,2.9999918937683105,-3.4111926555633545],"maxPosition",8,[1,1,5.999989032745361,-2.920604944229126]]],-1],0,0,[],[],[]],[[[5,"Skin-4",2261714205,["WINDOW_05_1_rig.003/Root/Left/Left_Window","WINDOW_05_1_rig.003/Root/Right/Right_Window"],[[[7,6.123234262925839e-17,1,-6.123234262925839e-17,0,-6.123234262925839e-17,6.123234262925839e-17,1,0,1,-6.123234262925839e-17,6.123234262925839e-17,0,3.133600950241089,0.02657400071620941,-4.635929107666016,1],[7,6.123234262925839e-17,-1,6.123234262925839e-17,0,6.123234262925839e-17,6.123234262925839e-17,1,0,-1,-6.123234262925839e-17,6.123234262925839e-17,0,-3.133600950241089,-0.9580410122871399,-4.557694911956787,1]],8,8]]],0,0,[],[],[]],[[[4,".bin",3376409279,[{"primitives":[{"primitiveMode":7,"jointMapIndex":0,"vertexBundelIndices":[0],"indexView":{"offset":449496,"length":13656,"count":6828,"stride":2}}],"vertexBundles":[{"view":{"offset":0,"length":449496,"count":6243,"stride":72},"attributes":[{"name":"a_position","format":32,"isNormalized":false},{"name":"a_normal","format":32,"isNormalized":false},{"name":"a_texCoord","format":21,"isNormalized":false},{"name":"a_tangent","format":44,"isNormalized":false},{"name":"a_joints","format":42,"isNormalized":false},{"name":"a_weights","format":44,"isNormalized":false}]}],"jointMaps":[[0,1]]},"minPosition",8,[1,-2,2.999993085861206,1.9206039905548096],"maxPosition",8,[1,0.9999963641166687,5.999990463256836,2.411191701889038]]],-1],0,0,[],[],[]],[[[5,"Skin-0",3128304054,["DOOR_01_1_rig/Root/Door"],[[[7,6.123234262925839e-17,1,-6.123234262925839e-17,0,-6.123234262925839e-17,6.123234262925839e-17,1,0,1,-6.123234262925839e-17,6.123234262925839e-17,0,-2.0008299350738525,-0.194473996758461,0.0019049999536946416,1]],8]]],0,0,[],[],[]],[[[4,".bin",4203392326,[{"primitives":[{"primitiveMode":7,"jointMapIndex":0,"vertexBundelIndices":[0],"indexView":{"offset":449496,"length":13656,"count":6828,"stride":2}}],"vertexBundles":[{"view":{"offset":0,"length":449496,"count":6243,"stride":72},"attributes":[{"name":"a_position","format":32,"isNormalized":false},{"name":"a_normal","format":32,"isNormalized":false},{"name":"a_texCoord","format":21,"isNormalized":false},{"name":"a_tangent","format":44,"isNormalized":false},{"name":"a_joints","format":42,"isNormalized":false},{"name":"a_weights","format":44,"isNormalized":false}]}],"jointMaps":[[0,1]]},"minPosition",8,[1,-2.4111931324005127,2.9999918937683105,-2],"maxPosition",8,[1,-1.9206054210662842,5.999989032745361,0.9999963641166687]]],-1],0,0,[],[],[]],[[[11,"House_01_material",[{"rasterizerState":{},"blendState":{"targets":[{}]},"depthStencilState":{}}],[{"USE_ALBEDO_MAP":true,"DCC_APP_NAME":0}],[[[{"albedoScale":1,"specularFactor":1,"shininessExponent":20,"emissiveScale":1},"mainColor",8,[4,4294967295],"specularColor",8,[4,4286348412],"emissive",8,[4,4278190080],"mainTexture",6,0]],11]]],0,0,[0,0],[4,5],[1,2]],[[[5,"Skin-2",1354997295,["WINDOW_05_1_rig/Root/Left/Left_Window","WINDOW_05_1_rig/Root/Right/Right_Window"],[[[7,6.123234262925839e-17,-1,6.123234262925839e-17,0,6.123234262925839e-17,6.123234262925839e-17,1,0,-1,-6.123234262925839e-17,6.123234262925839e-17,0,2.1335999965667725,-0.9734259843826294,-4.635929107666016,1],[7,6.123234262925839e-17,1,-6.123234262925839e-17,0,-6.123234262925839e-17,6.123234262925839e-17,1,0,1,-6.123234262925839e-17,6.123234262925839e-17,0,-2.1335999965667725,0.041958998888731,-4.557694911956787,1]],8,8]]],0,0,[],[],[]],[[[4,".bin",2839826276,[{"primitives":[{"primitiveMode":7,"jointMapIndex":0,"vertexBundelIndices":[0],"indexView":{"offset":450792,"length":13656,"count":6828,"stride":2}}],"vertexBundles":[{"view":{"offset":0,"length":450792,"count":6261,"stride":72},"attributes":[{"name":"a_position","format":32,"isNormalized":false},{"name":"a_normal","format":32,"isNormalized":false},{"name":"a_texCoord","format":21,"isNormalized":false},{"name":"a_tangent","format":44,"isNormalized":false},{"name":"a_joints","format":42,"isNormalized":false},{"name":"a_weights","format":44,"isNormalized":false}]}],"jointMaps":[[0,1]]},"minPosition",8,[1,0.9206046462059021,2.9999897480010986,-1.9999996423721313],"maxPosition",8,[1,1.411192774772644,5.999989986419678,1.0000009536743164]]],-1],0,0,[],[],[]],[[[4,".bin",1207285647,[{"primitives":[{"primitiveMode":7,"vertexBundelIndices":[0],"indexView":{"offset":57672,"length":1698,"count":849,"stride":2}}],"vertexBundles":[{"view":{"offset":0,"length":57672,"count":801,"stride":72},"attributes":[{"name":"a_position","format":32,"isNormalized":false},{"name":"a_normal","format":32,"isNormalized":false},{"name":"a_texCoord","format":21,"isNormalized":false},{"name":"a_tangent","format":44,"isNormalized":false},{"name":"a_joints","format":42,"isNormalized":false},{"name":"a_weights","format":44,"isNormalized":false}]}]},"minPosition",8,[1,0.000007999999979801942,-0.0019046751549467444,1.9475408792495728],"maxPosition",8,[1,1.0000090599060059,2.9999845027923584,2.055781364440918]]],-1],0,0,[],[],[]],[[[5,"Skin-3",3590397883,["WINDOW_05_1_rig.002/Root/Left/Left_Window","WINDOW_05_1_rig.002/Root/Right/Right_Window"],[[[7,1,0,0,0,0,1.2246468525851679e-16,0.9998999834060669,0,0,-1,1.224524297505612e-16,0,2.133600950241089,-0.9734259843826294,-4.635464668273926,1],[7,-1,1.2246468525851679e-16,1.224524297505612e-16,0,1.2246468525851679e-16,-1.2246468525851679e-16,0.9998999834060669,0,1.2246468525851679e-16,1,1.224524297505612e-16,0,-2.133600950241089,0.041958998888731,-4.5572381019592285,1]],8,8]]],0,0,[],[],[]],[[[12],[13,"House_08_rig",[-3,-4,-5,-6,-7],[[14,-2,[3,"efz7FO1AJfqZan3LJw426i"]]],[0,"57qokh7N5f2JzYe27xOPXK",null,null,null,-1,0]],[6,"DOOR_01_1_rig",1,[-8,-9],[0,"67RqIv5nRUHpbwont97g8h",null,null,null,1,0]],[6,"WINDOW_05_1_rig.001",1,[-10,-11],[0,"21rc0k5m1VgbY1V9iykR61",null,null,null,1,0]],[10,"Root",3,[-12,-13],[0,"7ecyFI2HtW4rF+BiTAvJ2N",null,null,null,1,0],[1,1,2.999993085861206,1],[3,-0.684805089904916,0.01787318834264526,-0.02535429391047512,0.7280657235161462],[1,1.000024676322937,1.000027060508728,1.0000401735305786],[1,-86.50776768358081,-0.49940963415820133,-3.520088103744666]],[6,"WINDOW_05_1_rig",1,[-14,-15],[0,"12TrUFqy1XJ5YjPiJ9lhpF",null,null,null,1,0]],[10,"Root",5,[-16,-17],[0,"36GBtlEcVZHYg1NH/dDHE3",null,null,null,1,0],[1,-2,2.9999918937683105,2],[3,-0.4663021217914879,-0.502181942003203,-0.5021585173780501,0.5274584834499552],[1,1.000024676322937,1.000027060508728,1.0000401735305786],[1,-86.50776698192409,-90.49940799724764,-3.5200906589377783]],[6,"WINDOW_05_1_rig.002",1,[-18,-19],[0,"2dQ5Mbd4RcT6fQPoKQLYST",null,null,null,1,0]],[10,"Root",7,[-20,-21],[0,"1dCb3Nh35fjZTNtu+nzB/6",null,null,null,1,0],[1,-2,2.9999918937683105,-2],[3,-0.025354293910475122,0.7280657235161464,0.6848050899049161,-0.017873188342645265],[1,1.000024676322937,1.000027060508728,1.0000401735305786],[1,-86.50776768358082,179.5005903658418,-3.520088103744668]],[6,"WINDOW_05_1_rig.003",1,[-22,-23],[0,"3fDTs7Q6FXirm255lAwnSx",null,null,null,1,0]],[10,"Root",9,[-24,-25],[0,"b3FnZULrlV7LBBZhvhxr+H",null,null,null,1,0],[1,1,2.9999918937683105,-3],[3,-0.5021585173780501,0.5274584834499552,0.4663021217914879,0.502181942003203],[1,1.000024676322937,1.000027060508728,1.0000401735305786],[1,-86.50776698192409,89.50059200275237,-3.5200906589377783]],[2,"Root",2,[[1,"Door",-26,[0,"71dSxR6tJWYrrf6tq3amMT",null,null,null,1,0],[1,-0.000007904877747932915,0.19448190927505493,-0.0011737341992557049],[3,-0.00015116088656666064,-0.7036333698991126,0.007100497857119751,0.7105277199694506],[1,1.0000814199447632,1.0000437498092651,0.9999667406082153],[1,0.5602473722311399,-89.44423126333635,0.5903245515107869]]],[0,"08B9B0lAJeVprY435WL9uj",null,null,null,1,0],[1,0.000007999999979801942,-0.000014999999621068127,2],[3,0.00017866818624928744,-0.007073247028550483,-0.7105279720193068,0.7036333833981184],[1,0.9999950528144836,0.9999563097953796,0.9999568462371826],[1,-134.70622656990034,-135.29385469518996,-89.20993264191254]],[7,"DOOR_01_1",2,[[8,-27,[3,"61H98/45lSvo6lkC2R0xRj"],[0],[9],1,1,2]],[0,"9ePuYjG9lc75gui6YLJUZb",null,null,null,1,0]],[2,"Left",4,[[1,"Left_Window",-28,[0,"a6XevLd7VQgqJYuC+ns3a6",null,null,null,1,0],[1,-0.000010804108569573145,1.6195725202560425,0.00006336749356705695],[3,-0.5946762784656964,0.04134008070779141,-0.013557629236530467,0.8027872148002528],[1,1.000014066696167,1.000009298324585,1.0000011920928955],[1,-72.95690192151224,2.8875933861036183,-4.067733265634579]]],[0,"4e9Os6m5pV0br76esqEit2",null,null,null,1,0],[1,0.0000026273705771018285,1.5028527975082397,-0.000007302834546862869],[3,0.014031947457920128,0.6193053663906367,0.7850230858113316,0.0016499556212426966],[1,0.9999610781669617,0.999953031539917,0.9999694228172302],[1,-103.4715637573208,-178.85451577033234,1.1443087264229888]],[2,"Right",4,[[1,"Right_Window",-29,[0,"33Amxzc89dwJ6jDR+swR/R",null,null,null,1,0],[1,-0.00008134394738590345,1.5404539108276367,0.00004910866482532583],[3,-0.5923631873884037,-0.035341568807764255,0.020362817048640375,0.8046379206966948],[1,0.9999727606773376,1.0000368356704712,0.9999468326568604],[1,-72.64962082002415,-1.8820220747764675,4.280507867795855]]],[0,"62uQ+IUKxZhaYtskWRxvW7",null,null,null,1,0],[1,0.0000026273705771018285,1.5028527975082397,-0.000007302834546862869],[3,0.5676325056444953,0.01322283151774142,0.0009382443539644388,0.8231753245572524],[1,1.0000027418136597,0.9999830722808838,0.999966025352478],[1,69.16771506017845,1.1865142056605997,0.9486378342394265]],[7,"WINDOW_05_1.001",3,[[8,-30,[3,"47nfGlVcxXOLpQrw9p+61p"],[3],[9],1,4,5]],[0,"0aapevrBxbpb+RiC8PRVGU",null,null,null,1,0]],[2,"Left",6,[[1,"Left_Window",-31,[0,"87Xs90hS9XkKUIHhKlpKIk",null,null,null,1,0],[1,-0.000010055387065222021,1.6195696592330933,0.000064710526203271],[3,-0.5946747708696382,0.04134027693302763,-0.01355749752153315,0.8027883236913687],[1,1.0000141859054565,1.0000184774398804,0.999997079372406],[1,-72.95668613311395,2.8876281249280327,-4.067729090944178]]],[0,"6bygMBvuNbBbWuVTddWdc6",null,null,null,1,0],[1,0.0000026273705771018285,1.5028527975082397,-0.000007302834546862869],[3,0.014031946592276091,0.6193048328475835,0.7850235067182556,0.0016499655242678576],[1,0.9999610781669617,0.999953031539917,0.9999644160270691],[1,-103.47164163986356,-178.85451577330122,1.144308777522641]],[2,"Right",6,[[1,"Right_Window",-32,[0,"5aQHkG90ZYmp6NDQcJJEy4",null,null,null,1,0],[1,-0.00008226869977079332,1.5404525995254517,0.00004973495379090309],[3,-0.5923631873884037,-0.035341568807764255,0.020362817048640375,0.8046379206966948],[1,0.9999727606773376,1.0000368356704712,0.9999468326568604],[1,-72.64962082002415,-1.8820220747764675,4.280507867795855]]],[0,"8cEUzevqhVjojX1CwKa9Ra",null,null,null,1,0],[1,0.0000026273705771018285,1.5028527975082397,-0.000007302834546862869],[3,0.5676325056444953,0.01322283151774142,0.0009382443539644388,0.8231753245572524],[1,1.0000027418136597,0.9999830722808838,0.999966025352478],[1,69.16771506017845,1.1865142056605997,0.9486378342394265]],[7,"WINDOW_05_1",5,[[8,-33,[3,"73YV1J+nlSXpmRR52FcPHX"],[6],[9],1,7,8]],[0,"89Z12x669Tc5prdbWBTWzB",null,null,null,1,0]],[2,"Left",8,[[1,"Left_Window",-34,[0,"5d6t4LWI1QDKDr2GBeyyNT",null,null,null,1,0],[1,-0.000011216619896003976,1.6195677518844604,0.00006418216798920184],[3,-0.5946747708696382,0.04134027693302763,-0.01355749752153315,0.8027883236913687],[1,1.0000141859054565,1.0000184774398804,1.0000970363616943],[1,-72.95668613311395,2.8876281249280327,-4.067729090944178]]],[0,"65HVzmZpdZNJQzdRrsRVr3",null,null,null,1,0],[1,0.000002565973545642919,1.5028527975082397,-0.000006306614523055032],[3,0.014031946592276091,0.6193048328475835,0.7850235067182556,0.0016499655242678576],[1,0.9999610781669617,0.999953031539917,0.9999644160270691],[1,-103.47164163986356,-178.85451577330122,1.144308777522641]],[2,"Right",8,[[1,"Right_Window",-35,[0,"ed0ABGOEZdvLOpdXBzJR3h",null,null,null,1,0],[1,-0.00008111006172839552,1.5404508113861084,0.000049176298489328474],[3,-0.5923631873884037,-0.035341568807764255,0.020362817048640375,0.8046379206966948],[1,0.9999727606773376,1.0000368356704712,1.0000468492507935],[1,-72.64962082002415,-1.8820220747764675,4.280507867795855]]],[0,"84rrtVrvtQio9Uo8AjuJGo",null,null,null,1,0],[1,0.000002565973545642919,1.5028527975082397,-0.000006306614523055032],[3,0.5676325056444953,0.01322283151774142,0.0009382443539644388,0.8231753245572524],[1,1.0000027418136597,0.9999830722808838,0.999966025352478],[1,69.16771506017845,1.1865142056605997,0.9486378342394265]],[7,"WINDOW_05_1.002",7,[[8,-36,[3,"4faBEsmGNYEqzoFYvChbOs"],[9],[9],1,10,11]],[0,"b0FjoO+epRzqSCSm2eN6BQ",null,null,null,1,0]],[2,"Left",10,[[1,"Left_Window",-37,[0,"9fDnFGzUhVEbH0o8u+fGIC",null,null,null,1,0],[1,-0.00001113411781261675,1.6195687055587769,0.000064471474615857],[3,-0.5946747708696382,0.04134027693302763,-0.01355749752153315,0.8027883236913687],[1,1.0000141859054565,1.0000184774398804,0.999997079372406],[1,-72.95668613311395,2.8876281249280327,-4.067729090944178]]],[0,"250C6OSlxYypbzBkJErQc5",null,null,null,1,0],[1,0.000002565973545642919,1.5028527975082397,-0.000006306614523055032],[3,0.014031946592276091,0.6193048328475835,0.7850235067182556,0.0016499655242678576],[1,0.9999610781669617,0.999953031539917,0.9999644160270691],[1,-103.47164163986356,-178.85451577330122,1.144308777522641]],[2,"Right",10,[[1,"Right_Window",-38,[0,"92awTdN5RWRK+HB9YPXW5M",null,null,null,1,0],[1,-0.00008119105768855661,1.5404517650604248,0.0000494720006827265],[3,-0.5923631873884037,-0.035341568807764255,0.020362817048640375,0.8046379206966948],[1,0.9999727606773376,1.0000368356704712,0.9999468326568604],[1,-72.64962082002415,-1.8820220747764675,4.280507867795855]]],[0,"dblwYnp3NYUae6TPPDeYCi",null,null,null,1,0],[1,0.000002565973545642919,1.5028527975082397,-0.000006306614523055032],[3,0.5676325056444953,0.01322283151774142,0.0009382443539644388,0.8231753245572524],[1,1.0000027418136597,0.9999830722808838,0.999966025352478],[1,69.16771506017845,1.1865142056605997,0.9486378342394265]],[7,"WINDOW_05_1.003",9,[[8,-39,[3,"15Y5WpwnRTDaXzzWEkv44b"],[12],[9],1,13,14]],[0,"7c5ONmIAFUuIi5nKX3b+BO",null,null,null,1,0]]],0,[0,6,1,0,1,1,0,-1,2,0,-2,3,0,-3,5,0,-4,7,0,-5,9,0,-1,11,0,-2,12,0,-1,4,0,-2,15,0,-1,13,0,-2,14,0,-1,6,0,-2,18,0,-1,16,0,-2,17,0,-1,8,0,-2,21,0,-1,19,0,-2,20,0,-1,10,0,-2,24,0,-1,22,0,-2,23,0,0,11,0,1,12,0,0,13,0,0,14,0,1,15,0,0,16,0,0,17,0,1,18,0,0,19,0,0,20,0,1,21,0,0,22,0,0,23,0,1,24,0,7,1,39],[0,0,0,0,0,0,0,0,0,0,0,0,0,0,0],[-1,2,3,-1,2,3,-1,2,3,-1,2,3,-1,2,3],[0,3,4,0,5,6,0,7,8,0,9,10,0,11,12]],[[[5,"Skin-1",3787673652,["WINDOW_05_1_rig.001/Root/Left/Left_Window","WINDOW_05_1_rig.001/Root/Right/Right_Window"],[[[7,-1,1.2246468525851679e-16,1.2246468525851679e-16,0,1.2246468525851679e-16,-1.2246468525851679e-16,1,0,1.2246468525851679e-16,1,1.2246468525851679e-16,0,1.1336009502410889,0.02657400071620941,-4.635932922363281,1],[7,1,0,0,0,0,1.2246468525851679e-16,1,0,0,-1,1.2246468525851679e-16,0,-1.1336009502410889,-0.9580420255661011,-4.55769681930542,1]],8,8]]],0,0,[],[],[]]]]
